analytics_ingest/__init__.py
analytics_ingest/ingest_client.py
analytics_ingest/internal/__init__.py
analytics_ingest/internal/schemas/__init__.py
analytics_ingest/internal/schemas/configuration_schema.py
analytics_ingest/internal/schemas/dtc_schema.py
analytics_ingest/internal/schemas/gps_schema.py
analytics_ingest/internal/schemas/ingest_config_schema.py
analytics_ingest/internal/schemas/message_schema.py
analytics_ingest/internal/schemas/network_schema.py
analytics_ingest/internal/schemas/signal_schema.py
analytics_ingest/internal/utils/__init__.py
analytics_ingest/internal/utils/batching.py
analytics_ingest/internal/utils/configuration.py
analytics_ingest/internal/utils/dtc.py
analytics_ingest/internal/utils/gps.py
analytics_ingest/internal/utils/graphql_executor.py
analytics_ingest/internal/utils/message.py
analytics_ingest/internal/utils/mutations.py
analytics_ingest/internal/utils/network.py
analytics_ingest/internal/utils/serialization.py
analytics_ingest/internal/utils/signal_buffer_manager.py
factories/__init__.py
factories/configuration.py
factories/dtc.py
factories/gps.py
factories/init_schema_factory.py
factories/message.py
factories/network_stats.py
factories/signal.py
analytics_ingest-0.1.78.dist-info/METADATA
analytics_ingest-0.1.78.dist-info/WHEEL
analytics_ingest-0.1.78.dist-info/top_level.txt
analytics_ingest-0.1.78.dist-info/RECORD
