Metadata-Version: 2.4
Name: analytics-ingest
Version: 0.1.78
Summary: - Updated the logic of flush and graphql. 
Author-email: Haseeb Saif Ullah <hsaif@intrepidcs.com>
License: MIT
Requires-Python: >=3.11
Requires-Dist: requests>=2.31
Requires-Dist: graphql-core>=3.2
Requires-Dist: pydantic>=2.5
Requires-Dist: more-itertools>=9.1.0
Provides-Extra: dev
Requires-Dist: black>=23.3.0; extra == "dev"
Requires-Dist: faker>=19.0; extra == "dev"
Requires-Dist: isort>=5.12.0; extra == "dev"
Requires-Dist: pre-commit>=3.5.0; extra == "dev"
Requires-Dist: pytest>=7.4.0; extra == "dev"
Requires-Dist: pytest-asyncio>=0.21.0; extra == "dev"
Requires-Dist: mypy>=1.7.0; extra == "dev"
